visual_attention/__init__.py
visual_attention/channel_attention.py
visual_attention/pixel_attention.py
visual_attention_tf-1.2.0.dist-info/LICENSE
visual_attention_tf-1.2.0.dist-info/METADATA
visual_attention_tf-1.2.0.dist-info/WHEEL
visual_attention_tf-1.2.0.dist-info/top_level.txt
visual_attention_tf-1.2.0.dist-info/RECORD
