Metadata-Version: 2.1
Name: visual-attention-tf
Version: 1.2.0
Summary: CNN Attention layer to be used with tf or tf.keras 
Home-page: https://github.com/vinayak19th/Visual_attention_tf
Author: Vinayak Sharma
Author-email: vinayak19th@gmail.com
License: MIT
Project-URL: Bug Tracker, https://github.com/vinayak19th/Visual_attention_tf/issues
Platform: UNKNOWN
Classifier: Programming Language :: Python :: 3
Classifier: License :: OSI Approved :: MIT License
Classifier: Operating System :: OS Independent
Requires-Python: >=3.6
Requires-Dist: tensorflow (>=2.2.0)
